flann-1.6.13.dist-info/DESCRIPTION.rst
flann-1.6.13.dist-info/METADATA
flann-1.6.13.dist-info/RECORD
flann-1.6.13.dist-info/WHEEL
flann-1.6.13.dist-info/metadata.json
flann-1.6.13.dist-info/top_level.txt
pyflann/__init__.py
pyflann/exceptions.py
pyflann/index.py
pyflann/bindings/__init__.py
pyflann/bindings/flann_ctypes.py
pyflann/io/__init__.py
pyflann/io/binary_dataset.py
pyflann/io/dat_dataset.py
pyflann/io/dataset.py
pyflann/io/hdf5_dataset.py
pyflann/io/npy_dataset.py
pyflann/util/__init__.py
pyflann/util/weave_tools.py
