Metadata-Version: 2.0
Name: flann
Version: 1.6.13
Summary: flann is the python 3.6 bindings for FLANN - Fast Library for Approximate Nearest Neighbors.
Home-page: https://github.com/pypa/flann
Author: Marius Muja & Gefu Tang, Maintainer: Russi Chatterjee
Author-email: root@ixaxaar.in
License: BSD
Keywords: Approximate Nearest Neighbors
Platform: UNKNOWN
Classifier: Programming Language :: Python :: 3
Classifier: Programming Language :: Python :: 3.6
Requires-Python: >=3
Provides-Extra: dev
Provides-Extra: test
Requires-Dist: numpy
Provides-Extra: dev
Requires-Dist: check-manifest; extra == 'dev'
Provides-Extra: test
Requires-Dist: coverage; extra == 'test'
